{"edges":[{"source":0,"target":646,"w":1.3},{"source":646,"target":41,"w":1.1},{"source":646,"target":44,"w":1.1},{"source":646,"target":46,"w":1.1},{"source":646,"target":77,"w":1.1},{"source":646,"target":134,"w":1.1},{"source":134,"target":146,"w":1.1},{"source":146,"target":114,"w":1.1},{"source":646,"target":164,"w":1.1},{"source":164,"target":152,"w":1.1},{"source":152,"target":37,"w":1.1},{"source":152,"target":49,"w":1.1},{"source":152,"target":69,"w":1.1},{"source":152,"target":121,"w":1.1},{"source":121,"target":51,"w":1.1},{"source":152,"target":122,"w":1.1},{"source":152,"target":162,"w":1.1},{"source":646,"target":173,"w":1.1},{"source":173,"target":149,"w":1.1},{"source":134,"target":174,"w":1.1},{"source":646,"target":183,"w":1.1},{"source":152,"target":194,"w":1.1},{"source":114,"target":199,"w":1.1},{"source":199,"target":72,"w":1.1},{"source":199,"target":74,"w":1.1},{"source":199,"target":125,"w":1.1},{"source":199,"target":167,"w":1.1},{"source":199,"target":187,"w":1.1},{"source":187,"target":71,"w":1.1},{"source":71,"target":61,"w":1.1},{"source":152,"target":211,"w":1.1},{"source":152,"target":224,"w":1.1},{"source":224,"target":223,"w":1.1},{"source":199,"target":237,"w":1.1},{"source":199,"target":256,"w":1.1},{"source":256,"target":118,"w":1.1},{"source":118,"target":18,"w":1.1},{"source":118,"target":150,"w":1.1},{"source":18,"target":236,"w":1.1},{"source":199,"target":260,"w":1.1},{"source":199,"target":262,"w":1.1},{"source":199,"target":264,"w":1.1},{"source":264,"target":151,"w":1.1},{"source":199,"target":270,"w":1.1},{"source":187,"target":272,"w":1.1},{"source":152,"target":292,"w":1.1},{"source":646,"target":293,"w":1.1},{"source":293,"target":169,"w":1.1},{"source":169,"target":230,"w":1.1},{"source":125,"target":310,"w":1.1},{"source":310,"target":5,"w":1.1},{"source":310,"target":24,"w":1.1},{"source":310,"target":94,"w":1.1},{"source":310,"target":259,"w":1.1},{"source":259,"target":248,"w":1.1},{"source":187,"target":311,"w":1.1},{"source":646,"target":312,"w":1.1},{"source":312,"target":10,"w":1.1},{"source":71,"target":313,"w":1.1},{"source":313,"target":21,"w":1.1},{"source":313,"target":63,"w":1.1},{"source":313,"target":90,"w":1.1},{"source":313,"target":157,"w":1.1},{"source":313,"target":202,"w":1.1},{"source":202,"target":48,"w":1.1},{"source":313,"target":245,"w":1.1},{"source":313,"target":299,"w":1.1},{"source":313,"target":300,"w":1.1},{"source":152,"target":329,"w":1.1},{"source":646,"target":336,"w":1.1},{"source":134,"target":343,"w":1.1},{"source":343,"target":198,"w":1.1},{"source":343,"target":267,"w":1.1},{"source":152,"target":350,"w":1.1},{"source":310,"target":351,"w":1.1},{"source":152,"target":359,"w":1.1},{"source":310,"target":360,"w":1.1},{"source":18,"target":361,"w":1.1},{"source":310,"target":364,"w":1.1},{"source":313,"target":369,"w":1.1},{"source":199,"target":390,"w":1.1},{"source":152,"target":392,"w":1.1},{"source":343,"target":412,"w":1.1},{"source":412,"target":268,"w":1.1},{"source":268,"target":344,"w":1.1},{"source":187,"target":417,"w":1.1},{"source":151,"target":430,"w":1.1},{"source":268,"target":431,"w":1.1},{"source":187,"target":438,"w":1.1},{"source":152,"target":443,"w":1.1},{"source":134,"target":444,"w":1.1},{"source":74,"target":452,"w":1.1},{"source":452,"target":182,"w":1.1},{"source":182,"target":176,"w":1.1},{"source":176,"target":119,"w":1.1},{"source":119,"target":97,"w":1.1},{"source":452,"target":273,"w":1.1},{"source":452,"target":368,"w":1.1},{"source":18,"target":476,"w":1.1},{"source":343,"target":482,"w":1.1},{"source":114,"target":515,"w":1.1},{"source":152,"target":528,"w":1.1},{"source":482,"target":555,"w":1.1},{"source":555,"target":383,"w":1.1},{"source":199,"target":578,"w":1.1},{"source":646,"target":580,"w":1.1},{"source":580,"target":420,"w":1.1},{"source":152,"target":583,"w":1.1},{"source":152,"target":588,"w":1.1},{"source":311,"target":592,"w":1.1},{"source":199,"target":598,"w":1.1},{"source":199,"target":600,"w":1.1},{"source":152,"target":606,"w":1.1},{"source":149,"target":609,"w":1.1},{"source":151,"target":612,"w":1.1},{"source":152,"target":614,"w":1.1},{"source":223,"target":619,"w":1.1},{"source":619,"target":626,"w":1.1},{"source":272,"target":629,"w":1.1},{"source":629,"target":111,"w":1.1},{"source":629,"target":113,"w":1.1},{"source":629,"target":381,"w":1.1},{"source":152,"target":632,"w":1.1},{"source":259,"target":634,"w":1.1},{"source":634,"target":405,"w":1.1},{"source":405,"target":20,"w":1.1},{"source":20,"target":302,"w":1.1},{"source":20,"target":496,"w":1.1},{"source":199,"target":644,"w":1.1},{"source":644,"target":218,"w":1.1},{"source":218,"target":12,"w":1.1},{"source":218,"target":126,"w":1.1},{"source":218,"target":225,"w":1.1},{"source":12,"target":391,"w":1.1},{"source":173,"target":645,"w":1.1},{"source":152,"target":649,"w":1.1},{"source":199,"target":655,"w":1.1},{"source":152,"target":658,"w":1.1},{"source":199,"target":665,"w":1.1},{"source":150,"target":668,"w":1.1},{"source":668,"target":638,"w":1.1},{"source":152,"target":669,"w":1.1},{"source":199,"target":672,"w":1.1},{"source":152,"target":677,"w":1.1},{"source":134,"target":679,"w":1.1},{"source":391,"target":681,"w":1.1},{"source":681,"target":246,"w":1.1},{"source":681,"target":403,"w":1.1},{"source":681,"target":424,"w":1.1},{"source":629,"target":684,"w":1.1},{"source":684,"target":325,"w":1.1},{"source":325,"target":287,"w":1.1},{"source":325,"target":379,"w":1.1},{"source":684,"target":478,"w":1.1},{"source":199,"target":699,"w":1.1},{"source":417,"target":704,"w":1.1},{"source":152,"target":709,"w":1.1},{"source":77,"target":711,"w":1.1},{"source":152,"target":721,"w":1.1},{"source":646,"target":732,"w":1.1},{"source":313,"target":733,"w":1.1},{"source":152,"target":736,"w":1.1},{"source":152,"target":737,"w":1.1},{"source":114,"target":738,"w":1.1},{"source":310,"target":739,"w":1.1},{"source":310,"target":742,"w":1.1},{"source":403,"target":743,"w":1.1},{"source":743,"target":62,"w":1.1},{"source":743,"target":323,"w":1.1},{"source":743,"target":423,"w":1.1},{"source":199,"target":752,"w":1.1},{"source":151,"target":755,"w":1.1},{"source":152,"target":760,"w":1.1},{"source":118,"target":761,"w":1.1},{"source":152,"target":762,"w":1.1},{"source":152,"target":767,"w":1.1},{"source":146,"target":769,"w":1.1},{"source":152,"target":779,"w":1.1},{"source":302,"target":781,"w":1.1},{"source":151,"target":782,"w":1.1},{"source":152,"target":783,"w":1.1},{"source":646,"target":784,"w":1.1},{"source":646,"target":792,"w":1.1},{"source":792,"target":340,"w":1.1},{"source":272,"target":793,"w":1.1},{"source":793,"target":696,"w":1.1},{"source":187,"target":794,"w":1.1},{"source":199,"target":796,"w":1.1},{"source":796,"target":601,"w":1.1},{"source":796,"target":688,"w":1.1},{"source":412,"target":802,"w":1.1},{"source":152,"target":805,"w":1.1},{"source":202,"target":807,"w":1.1},{"source":709,"target":818,"w":1.1},{"source":818,"target":155,"w":1.1},{"source":818,"target":705,"w":1.1},{"source":150,"target":821,"w":1.1},{"source":555,"target":838,"w":1.1},{"source":152,"target":843,"w":1.1},{"source":152,"target":846,"w":1.1},{"source":152,"target":858,"w":1.1},{"source":152,"target":859,"w":1.1},{"source":646,"target":860,"w":1.1},{"source":152,"target":861,"w":1.1},{"source":861,"target":2,"w":1.1},{"source":199,"target":862,"w":1.1},{"source":149,"target":864,"w":1.1},{"source":218,"target":865,"w":1.1},{"source":169,"target":870,"w":1.1},{"source":202,"target":872,"w":1.1},{"source":668,"target":875,"w":1.1},{"source":313,"target":883,"w":1.1},{"source":310,"target":884,"w":1.1},{"source":646,"target":887,"w":1.1},{"source":887,"target":82,"w":1.1},{"source":887,"target":701,"w":1.1},{"source":149,"target":888,"w":1.1},{"source":424,"target":893,"w":1.1},{"source":151,"target":896,"w":1.1},{"source":199,"target":901,"w":1.1},{"source":299,"target":918,"w":1.1},{"source":134,"target":920,"w":1.1},{"source":668,"target":926,"w":1.1},{"source":926,"target":4,"w":1.1},{"source":681,"target":935,"w":1.1},{"source":272,"target":946,"w":1.1},{"source":946,"target":124,"w":1.1},{"source":946,"target":902,"w":1.1},{"source":902,"target":663,"w":1.1},{"source":194,"target":947,"w":1.1},{"source":947,"target":878,"w":1.1},{"source":878,"target":455,"w":1.1},{"source":681,"target":953,"w":1.1},{"source":199,"target":958,"w":1.1},{"source":313,"target":963,"w":1.1},{"source":963,"target":342,"w":1.1},{"source":268,"target":969,"w":1.1},{"source":350,"target":1,"w":1.3},{"source":742,"target":3,"w":1.3},{"source":199,"target":7,"w":1.3},{"source":268,"target":8,"w":1.3},{"source":310,"target":11,"w":1.3},{"source":169,"target":13,"w":1.3},{"source":313,"target":16,"w":1.3},{"source":152,"target":17,"w":1.3},{"source":18,"target":23,"w":1.3},{"source":146,"target":25,"w":1.3},{"source":187,"target":28,"w":1.3},{"source":7,"target":29,"w":1.3},{"source":223,"target":30,"w":1.3},{"source":146,"target":31,"w":1.3},{"source":711,"target":32,"w":1.3},{"source":126,"target":34,"w":1.3},{"source":164,"target":35,"w":1.3},{"source":646,"target":38,"w":1.3},{"source":313,"target":42,"w":1.3},{"source":63,"target":43,"w":1.3},{"source":187,"target":45,"w":1.3},{"source":268,"target":47,"w":1.3},{"source":629,"target":52,"w":1.3},{"source":71,"target":54,"w":1.3},{"source":54,"target":402,"w":1.1},{"source":646,"target":55,"w":1.3},{"source":164,"target":57,"w":1.3},{"source":402,"target":58,"w":1.3},{"source":38,"target":60,"w":1.3},{"source":310,"target":67,"w":1.3},{"source":878,"target":70,"w":1.3},{"source":646,"target":78,"w":1.3},{"source":78,"target":748,"w":1.1},{"source":807,"target":79,"w":1.3},{"source":452,"target":80,"w":1.3},{"source":187,"target":81,"w":1.3},{"source":202,"target":83,"w":1.3},{"source":646,"target":86,"w":1.3},{"source":793,"target":87,"w":1.3},{"source":646,"target":91,"w":1.3},{"source":313,"target":93,"w":1.3},{"source":626,"target":95,"w":1.3},{"source":152,"target":102,"w":1.3},{"source":199,"target":107,"w":1.3},{"source":619,"target":112,"w":1.3},{"source":112,"target":40,"w":1.3},{"source":187,"target":116,"w":1.3},{"source":629,"target":120,"w":1.3},{"source":629,"target":127,"w":1.3},{"source":127,"target":33,"w":1.3},{"source":187,"target":132,"w":1.3},{"source":199,"target":137,"w":1.3},{"source":583,"target":138,"w":1.3},{"source":41,"target":144,"w":1.3},{"source":144,"target":100,"w":1.3},{"source":144,"target":117,"w":1.3},{"source":18,"target":145,"w":1.3},{"source":807,"target":148,"w":1.3},{"source":901,"target":154,"w":1.3},{"source":310,"target":156,"w":1.3},{"source":52,"target":158,"w":1.3},{"source":887,"target":159,"w":1.3},{"source":268,"target":160,"w":1.3},{"source":743,"target":161,"w":1.3},{"source":199,"target":163,"w":1.3},{"source":18,"target":165,"w":1.3},{"source":152,"target":166,"w":1.3},{"source":69,"target":171,"w":1.3},{"source":152,"target":175,"w":1.3},{"source":164,"target":178,"w":1.3},{"source":629,"target":181,"w":1.3},{"source":555,"target":185,"w":1.3},{"source":646,"target":188,"w":1.3},{"source":646,"target":190,"w":1.3},{"source":187,"target":193,"w":1.3},{"source":646,"target":195,"w":1.3},{"source":901,"target":200,"w":1.3},{"source":150,"target":201,"w":1.3},{"source":807,"target":208,"w":1.3},{"source":336,"target":210,"w":1.3},{"source":51,"target":212,"w":1.3},{"source":796,"target":216,"w":1.3},{"source":259,"target":217,"w":1.3},{"source":217,"target":96,"w":1.3},{"source":61,"target":219,"w":1.3},{"source":219,"target":242,"w":1.1},{"source":219,"target":319,"w":1.1},{"source":219,"target":698,"w":1.1},{"source":219,"target":708,"w":1.1},{"source":219,"target":922,"w":1.1},{"source":219,"target":177,"w":1.3},{"source":152,"target":221,"w":1.3},{"source":121,"target":227,"w":1.3},{"source":152,"target":232,"w":1.3},{"source":268,"target":233,"w":1.3},{"source":144,"target":234,"w":1.3},{"source":94,"target":235,"w":1.3},{"source":187,"target":240,"w":1.3},{"source":62,"target":247,"w":1.3},{"source":259,"target":249,"w":1.3},{"source":646,"target":250,"w":1.3},{"source":202,"target":251,"w":1.3},{"source":310,"target":253,"w":1.3},{"source":629,"target":257,"w":1.3},{"source":10,"target":265,"w":1.3},{"source":555,"target":274,"w":1.3},{"source":893,"target":276,"w":1.3},{"source":224,"target":282,"w":1.3},{"source":282,"target":231,"w":1.3},{"source":310,"target":285,"w":1.3},{"source":62,"target":294,"w":1.3},{"source":424,"target":297,"w":1.3},{"source":152,"target":301,"w":1.3},{"source":134,"target":304,"w":1.3},{"source":310,"target":317,"w":1.3},{"source":646,"target":320,"w":1.3},{"source":344,"target":324,"w":1.3},{"source":62,"target":326,"w":1.3},{"source":134,"target":334,"w":1.3},{"source":334,"target":905,"w":1.1},{"source":807,"target":335,"w":1.3},{"source":443,"target":337,"w":1.3},{"source":146,"target":338,"w":1.3},{"source":807,"target":341,"w":1.3},{"source":79,"target":349,"w":1.3},{"source":349,"target":220,"w":1.3},{"source":94,"target":352,"w":1.3},{"source":187,"target":355,"w":1.3},{"source":807,"target":362,"w":1.3},{"source":235,"target":363,"w":1.3},{"source":319,"target":365,"w":1.3},{"source":114,"target":366,"w":1.3},{"source":202,"target":370,"w":1.3},{"source":629,"target":374,"w":1.3},{"source":41,"target":378,"w":1.3},{"source":378,"target":382,"w":1.3},{"source":438,"target":384,"w":1.3},{"source":383,"target":385,"w":1.3},{"source":969,"target":387,"w":1.3},{"source":920,"target":388,"w":1.3},{"source":268,"target":389,"w":1.3},{"source":963,"target":394,"w":1.3},{"source":646,"target":396,"w":1.3},{"source":378,"target":399,"w":1.3},{"source":629,"target":400,"w":1.3},{"source":926,"target":401,"w":1.3},{"source":444,"target":404,"w":1.3},{"source":404,"target":19,"w":1.3},{"source":404,"target":139,"w":1.3},{"source":404,"target":286,"w":1.3},{"source":807,"target":413,"w":1.3},{"source":443,"target":415,"w":1.3},{"source":199,"target":416,"w":1.3},{"source":632,"target":428,"w":1.3},{"source":361,"target":434,"w":1.3},{"source":708,"target":440,"w":1.3},{"source":313,"target":441,"w":1.3},{"source":887,"target":442,"w":1.3},{"source":121,"target":445,"w":1.3},{"source":424,"target":446,"w":1.3},{"source":310,"target":447,"w":1.3},{"source":646,"target":448,"w":1.3},{"source":202,"target":449,"w":1.3},{"source":449,"target":109,"w":1.3},{"source":202,"target":456,"w":1.3},{"source":37,"target":457,"w":1.3},{"source":457,"target":9,"w":1.3},{"source":457,"target":123,"w":1.3},{"source":457,"target":331,"w":1.3},{"source":146,"target":460,"w":1.3},{"source":449,"target":462,"w":1.3},{"source":462,"target":105,"w":1.3},{"source":273,"target":468,"w":1.3},{"source":152,"target":475,"w":1.3},{"source":167,"target":483,"w":1.3},{"source":858,"target":486,"w":1.3},{"source":486,"target":697,"w":1.1},{"source":77,"target":493,"w":1.3},{"source":187,"target":497,"w":1.3},{"source":497,"target":64,"w":1.3},{"source":583,"target":502,"w":1.3},{"source":634,"target":505,"w":1.3},{"source":152,"target":513,"w":1.3},{"source":513,"target":75,"w":1.3},{"source":41,"target":531,"w":1.3},{"source":482,"target":543,"w":1.3},{"source":457,"target":557,"w":1.3},{"source":457,"target":567,"w":1.3},{"source":202,"target":569,"w":1.3},{"source":946,"target":570,"w":1.3},{"source":555,"target":571,"w":1.3},{"source":157,"target":574,"w":1.3},{"source":218,"target":575,"w":1.3},{"source":202,"target":576,"w":1.3},{"source":646,"target":577,"w":1.3},{"source":150,"target":579,"w":1.3},{"source":646,"target":581,"w":1.3},{"source":78,"target":582,"w":1.3},{"source":300,"target":584,"w":1.3},{"source":259,"target":585,"w":1.3},{"source":359,"target":586,"w":1.3},{"source":586,"target":372,"w":1.3},{"source":445,"target":587,"w":1.3},{"source":587,"target":129,"w":1.3},{"source":199,"target":589,"w":1.3},{"source":90,"target":590,"w":1.3},{"source":590,"target":191,"w":1.3},{"source":369,"target":593,"w":1.3},{"source":860,"target":594,"w":1.3},{"source":299,"target":595,"w":1.3},{"source":629,"target":596,"w":1.3},{"source":187,"target":603,"w":1.3},{"source":171,"target":604,"w":1.3},{"source":350,"target":605,"w":1.3},{"source":114,"target":611,"w":1.3},{"source":743,"target":615,"w":1.3},{"source":445,"target":616,"w":1.3},{"source":616,"target":303,"w":1.3},{"source":236,"target":617,"w":1.3},{"source":311,"target":618,"w":1.3},{"source":580,"target":620,"w":1.3},{"source":378,"target":621,"w":1.3},{"source":621,"target":565,"w":1.1},{"source":114,"target":622,"w":1.3},{"source":807,"target":624,"w":1.3},{"source":202,"target":627,"w":1.3},{"source":152,"target":633,"w":1.3},{"source":152,"target":637,"w":1.3},{"source":248,"target":640,"w":1.3},{"source":438,"target":642,"w":1.3},{"source":118,"target":648,"w":1.3},{"source":125,"target":650,"w":1.3},{"source":650,"target":659,"w":1.1},{"source":646,"target":651,"w":1.3},{"source":476,"target":652,"w":1.3},{"source":807,"target":653,"w":1.3},{"source":438,"target":657,"w":1.3},{"source":793,"target":661,"w":1.3},{"source":378,"target":662,"w":1.3},{"source":199,"target":664,"w":1.3},{"source":150,"target":666,"w":1.3},{"source":646,"target":667,"w":1.3},{"source":668,"target":670,"w":1.3},{"source":739,"target":673,"w":1.3},{"source":709,"target":674,"w":1.3},{"source":18,"target":676,"w":1.3},{"source":793,"target":678,"w":1.3},{"source":149,"target":680,"w":1.3},{"source":144,"target":682,"w":1.3},{"source":313,"target":683,"w":1.3},{"source":683,"target":68,"w":1.1},{"source":151,"target":686,"w":1.3},{"source":199,"target":690,"w":1.3},{"source":457,"target":691,"w":1.3},{"source":452,"target":692,"w":1.3},{"source":152,"target":694,"w":1.3},{"source":629,"target":700,"w":1.3},{"source":219,"target":702,"w":1.3},{"source":146,"target":703,"w":1.3},{"source":449,"target":706,"w":1.3},{"source":145,"target":707,"w":1.3},{"source":152,"target":713,"w":1.3},{"source":259,"target":714,"w":1.3},{"source":629,"target":716,"w":1.3},{"source":187,"target":717,"w":1.3},{"source":164,"target":719,"w":1.3},{"source":629,"target":720,"w":1.3},{"source":457,"target":722,"w":1.3},{"source":646,"target":723,"w":1.3},{"source":580,"target":724,"w":1.3},{"source":169,"target":729,"w":1.3},{"source":0,"target":731,"w":1.3},{"source":731,"target":27,"w":1.3},{"source":731,"target":564,"w":1.3},{"source":793,"target":734,"w":1.3},{"source":71,"target":744,"w":1.3},{"source":187,"target":745,"w":1.3},{"source":12,"target":746,"w":1.3},{"source":325,"target":749,"w":1.3},{"source":71,"target":750,"w":1.3},{"source":187,"target":757,"w":1.3},{"source":580,"target":758,"w":1.3},{"source":455,"target":763,"w":1.3},{"source":199,"target":764,"w":1.3},{"source":445,"target":766,"w":1.3},{"source":887,"target":771,"w":1.3},{"source":555,"target":772,"w":1.3},{"source":646,"target":775,"w":1.3},{"source":344,"target":776,"w":1.3},{"source":55,"target":778,"w":1.3},{"source":778,"target":495,"w":1.3},{"source":893,"target":785,"w":1.3},{"source":72,"target":787,"w":1.3},{"source":793,"target":788,"w":1.3},{"source":245,"target":795,"w":1.3},{"source":151,"target":797,"w":1.3},{"source":424,"target":798,"w":1.3},{"source":798,"target":316,"w":1.3},{"source":316,"target":153,"w":1.3},{"source":798,"target":747,"w":1.3},{"source":282,"target":799,"w":1.3},{"source":169,"target":800,"w":1.3},{"source":5,"target":801,"w":1.3},{"source":801,"target":454,"w":1.3},{"source":672,"target":804,"w":1.3},{"source":152,"target":806,"w":1.3},{"source":2,"target":809,"w":1.3},{"source":16,"target":810,"w":1.3},{"source":310,"target":811,"w":1.3},{"source":684,"target":814,"w":1.3},{"source":402,"target":815,"w":1.3},{"source":268,"target":816,"w":1.3},{"source":452,"target":819,"w":1.3},{"source":645,"target":822,"w":1.3},{"source":183,"target":823,"w":1.3},{"source":114,"target":824,"w":1.3},{"source":311,"target":826,"w":1.3},{"source":199,"target":827,"w":1.3},{"source":646,"target":830,"w":1.3},{"source":299,"target":831,"w":1.3},{"source":199,"target":832,"w":1.3},{"source":18,"target":834,"w":1.3},{"source":383,"target":839,"w":1.3},{"source":839,"target":106,"w":1.3},{"source":359,"target":840,"w":1.3},{"source":840,"target":436,"w":1.3},{"source":202,"target":842,"w":1.3},{"source":231,"target":844,"w":1.3},{"source":183,"target":845,"w":1.3},{"source":634,"target":847,"w":1.3},{"source":847,"target":914,"w":1.1},{"source":313,"target":849,"w":1.3},{"source":176,"target":850,"w":1.3},{"source":632,"target":851,"w":1.3},{"source":311,"target":853,"w":1.3},{"source":378,"target":854,"w":1.3},{"source":365,"target":855,"w":1.3},{"source":855,"target":263,"w":1.3},{"source":144,"target":857,"w":1.3},{"source":152,"target":863,"w":1.3},{"source":146,"target":866,"w":1.3},{"source":158,"target":867,"w":1.3},{"source":62,"target":869,"w":1.3},{"source":683,"target":871,"w":1.3},{"source":946,"target":873,"w":1.3},{"source":364,"target":874,"w":1.3},{"source":874,"target":628,"w":1.3},{"source":187,"target":876,"w":1.3},{"source":846,"target":881,"w":1.3},{"source":187,"target":882,"w":1.3},{"source":646,"target":885,"w":1.3},{"source":452,"target":889,"w":1.3},{"source":313,"target":891,"w":1.3},{"source":199,"target":892,"w":1.3},{"source":253,"target":895,"w":1.3},{"source":165,"target":897,"w":1.3},{"source":897,"target":481,"w":1.3},{"source":646,"target":898,"w":1.3},{"source":200,"target":899,"w":1.3},{"source":90,"target":903,"w":1.3},{"source":152,"target":906,"w":1.3},{"source":884,"target":907,"w":1.3},{"source":152,"target":908,"w":1.3},{"source":443,"target":911,"w":1.3},{"source":20,"target":915,"w":1.3},{"source":580,"target":916,"w":1.3},{"source":313,"target":917,"w":1.3},{"source":20,"target":919,"w":1.3},{"source":629,"target":921,"w":1.3},{"source":152,"target":924,"w":1.3},{"source":302,"target":925,"w":1.3},{"source":144,"target":927,"w":1.3},{"source":927,"target":213,"w":1.3},{"source":778,"target":928,"w":1.3},{"source":614,"target":930,"w":1.3},{"source":887,"target":931,"w":1.3},{"source":963,"target":932,"w":1.3},{"source":152,"target":933,"w":1.3},{"source":118,"target":936,"w":1.3},{"source":62,"target":937,"w":1.3},{"source":313,"target":940,"w":1.3},{"source":629,"target":941,"w":1.3},{"source":457,"target":942,"w":1.3},{"source":359,"target":943,"w":1.3},{"source":268,"target":945,"w":1.3},{"source":268,"target":948,"w":1.3},{"source":165,"target":949,"w":1.3},{"source":302,"target":951,"w":1.3},{"source":860,"target":952,"w":1.3},{"source":248,"target":956,"w":1.3},{"source":61,"target":959,"w":1.3},{"source":146,"target":961,"w":1.3},{"source":125,"target":962,"w":1.3},{"source":887,"target":964,"w":1.3},{"source":452,"target":965,"w":1.3},{"source":965,"target":422,"w":1.3},{"source":965,"target":458,"w":1.3},{"source":965,"target":886,"w":1.3},{"source":965,"target":954,"w":1.3},{"source":646,"target":966,"w":1.3},{"source":96,"target":970,"w":1.3},{"source":121,"target":6,"w":1.5},{"source":71,"target":14,"w":1.5},{"source":37,"target":15,"w":1.5},{"source":37,"target":22,"w":1.5},{"source":390,"target":26,"w":1.5},{"source":646,"target":76,"w":1.5},{"source":646,"target":88,"w":1.5},{"source":926,"target":89,"w":1.5},{"source":125,"target":92,"w":1.5},{"source":893,"target":98,"w":1.5},{"source":646,"target":99,"w":1.5},{"source":430,"target":101,"w":1.5},{"source":865,"target":103,"w":1.5},{"source":646,"target":108,"w":1.5},{"source":737,"target":110,"w":1.5},{"source":194,"target":128,"w":1.5},{"source":925,"target":131,"w":1.5},{"source":898,"target":133,"w":1.5},{"source":149,"target":136,"w":1.5},{"source":146,"target":141,"w":1.5},{"source":646,"target":147,"w":1.5},{"source":384,"target":170,"w":1.5},{"source":438,"target":172,"w":1.5},{"source":41,"target":179,"w":1.5},{"source":360,"target":180,"w":1.5},{"source":381,"target":184,"w":1.5},{"source":63,"target":186,"w":1.5},{"source":896,"target":189,"w":1.5},{"source":78,"target":197,"w":1.5},{"source":77,"target":204,"w":1.5},{"source":169,"target":206,"w":1.5},{"source":146,"target":209,"w":1.5},{"source":646,"target":214,"w":1.5},{"source":619,"target":215,"w":1.5},{"source":199,"target":222,"w":1.5},{"source":151,"target":228,"w":1.5},{"source":44,"target":238,"w":1.5},{"source":146,"target":239,"w":1.5},{"source":146,"target":241,"w":1.5},{"source":405,"target":243,"w":1.5},{"source":646,"target":244,"w":1.5},{"source":708,"target":254,"w":1.5},{"source":114,"target":255,"w":1.5},{"source":887,"target":258,"w":1.5},{"source":580,"target":261,"w":1.5},{"source":94,"target":266,"w":1.5},{"source":646,"target":269,"w":1.5},{"source":257,"target":271,"w":1.5},{"source":118,"target":280,"w":1.5},{"source":187,"target":284,"w":1.5},{"source":646,"target":288,"w":1.5},{"source":646,"target":289,"w":1.5},{"source":162,"target":290,"w":1.5},{"source":587,"target":296,"w":1.5},{"source":351,"target":298,"w":1.5},{"source":937,"target":305,"w":1.5},{"source":158,"target":306,"w":1.5},{"source":405,"target":308,"w":1.5},{"source":146,"target":314,"w":1.5},{"source":167,"target":315,"w":1.5},{"source":18,"target":318,"w":1.5},{"source":668,"target":322,"w":1.5},{"source":24,"target":330,"w":1.5},{"source":245,"target":333,"w":1.5},{"source":223,"target":339,"w":1.5},{"source":646,"target":345,"w":1.5},{"source":40,"target":348,"w":1.5},{"source":146,"target":353,"w":1.5},{"source":125,"target":354,"w":1.5},{"source":94,"target":356,"w":1.5},{"source":646,"target":358,"w":1.5},{"source":113,"target":375,"w":1.5},{"source":29,"target":377,"w":1.5},{"source":893,"target":380,"w":1.5},{"source":287,"target":393,"w":1.5},{"source":125,"target":395,"w":1.5},{"source":146,"target":406,"w":1.5},{"source":872,"target":408,"w":1.5},{"source":174,"target":411,"w":1.5},{"source":237,"target":421,"w":1.5},{"source":555,"target":425,"w":1.5},{"source":830,"target":426,"w":1.5},{"source":245,"target":429,"w":1.5},{"source":311,"target":439,"w":1.5},{"source":334,"target":465,"w":1.5},{"source":173,"target":467,"w":1.5},{"source":49,"target":472,"w":1.5},{"source":482,"target":477,"w":1.5},{"source":646,"target":480,"w":1.5},{"source":821,"target":484,"w":1.5},{"source":313,"target":487,"w":1.5},{"source":482,"target":490,"w":1.5},{"source":872,"target":504,"w":1.5},{"source":199,"target":518,"w":1.5},{"source":482,"target":522,"w":1.5},{"source":262,"target":533,"w":1.5},{"source":94,"target":556,"w":1.5},{"source":422,"target":566,"w":1.5},{"source":187,"target":568,"w":1.5},{"source":268,"target":572,"w":1.5},{"source":646,"target":573,"w":1.5},{"source":679,"target":602,"w":1.5},{"source":183,"target":607,"w":1.5},{"source":96,"target":610,"w":1.5},{"source":646,"target":613,"w":1.5},{"source":152,"target":623,"w":1.5},{"source":174,"target":625,"w":1.5},{"source":626,"target":630,"w":1.5},{"source":195,"target":631,"w":1.5},{"source":149,"target":636,"w":1.5},{"source":629,"target":639,"w":1.5},{"source":365,"target":647,"w":1.5},{"source":310,"target":654,"w":1.5},{"source":646,"target":656,"w":1.5},{"source":646,"target":660,"w":1.5},{"source":646,"target":671,"w":1.5},{"source":629,"target":675,"w":1.5},{"source":41,"target":685,"w":1.5},{"source":893,"target":687,"w":1.5},{"source":646,"target":693,"w":1.5},{"source":118,"target":695,"w":1.5},{"source":646,"target":710,"w":1.5},{"source":149,"target":712,"w":1.5},{"source":121,"target":718,"w":1.5},{"source":310,"target":725,"w":1.5},{"source":832,"target":728,"w":1.5},{"source":199,"target":730,"w":1.5},{"source":310,"target":735,"w":1.5},{"source":121,"target":740,"w":1.5},{"source":134,"target":753,"w":1.5},{"source":807,"target":754,"w":1.5},{"source":646,"target":756,"w":1.5},{"source":35,"target":765,"w":1.5},{"source":342,"target":768,"w":1.5},{"source":187,"target":770,"w":1.5},{"source":646,"target":773,"w":1.5},{"source":125,"target":774,"w":1.5},{"source":121,"target":780,"w":1.5},{"source":457,"target":786,"w":1.5},{"source":444,"target":789,"w":1.5},{"source":452,"target":790,"w":1.5},{"source":646,"target":791,"w":1.5},{"source":121,"target":803,"w":1.5},{"source":412,"target":808,"w":1.5},{"source":310,"target":812,"w":1.5},{"source":152,"target":813,"w":1.5},{"source":224,"target":817,"w":1.5},{"source":156,"target":820,"w":1.5},{"source":146,"target":828,"w":1.5},{"source":364,"target":829,"w":1.5},{"source":445,"target":833,"w":1.5},{"source":569,"target":835,"w":1.5},{"source":114,"target":836,"w":1.5},{"source":149,"target":837,"w":1.5},{"source":646,"target":841,"w":1.5},{"source":223,"target":848,"w":1.5},{"source":187,"target":868,"w":1.5},{"source":187,"target":880,"w":1.5},{"source":149,"target":890,"w":1.5},{"source":193,"target":894,"w":1.5},{"source":90,"target":900,"w":1.5},{"source":157,"target":909,"w":1.5},{"source":152,"target":910,"w":1.5},{"source":51,"target":913,"w":1.5},{"source":41,"target":923,"w":1.5},{"source":646,"target":929,"w":1.5},{"source":646,"target":934,"w":1.5},{"source":311,"target":938,"w":1.5},{"source":626,"target":939,"w":1.5},{"source":646,"target":944,"w":1.5},{"source":223,"target":950,"w":1.5},{"source":478,"target":957,"w":1.5},{"source":555,"target":960,"w":1.5},{"source":41,"target":967,"w":1.5},{"source":646,"target":968,"w":1.5},{"source":253,"target":65,"w":1.7},{"source":513,"target":66,"w":1.7},{"source":443,"target":135,"w":1.7},{"source":929,"target":226,"w":1.7},{"source":55,"target":291,"w":1.7},{"source":46,"target":295,"w":1.7},{"source":310,"target":321,"w":1.7},{"source":105,"target":488,"w":1.7},{"source":649,"target":489,"w":1.7},{"source":343,"target":516,"w":1.7},{"source":609,"target":521,"w":1.7},{"source":883,"target":591,"w":1.7},{"source":216,"target":643,"w":1.7},{"source":3,"target":852,"w":1.7},{"source":256,"target":36,"w":1.9},{"source":41,"target":59,"w":1.9},{"source":167,"target":84,"w":1.9},{"source":46,"target":115,"w":1.9},{"source":0,"target":130,"w":1.9},{"source":18,"target":140,"w":1.9},{"source":134,"target":143,"w":1.9},{"source":77,"target":192,"w":1.9},{"source":41,"target":196,"w":1.9},{"source":114,"target":252,"w":1.9},{"source":41,"target":275,"w":1.9},{"source":114,"target":277,"w":1.9},{"source":41,"target":279,"w":1.9},{"source":41,"target":281,"w":1.9},{"source":794,"target":328,"w":1.9},{"source":44,"target":346,"w":1.9},{"source":134,"target":347,"w":1.9},{"source":46,"target":357,"w":1.9},{"source":77,"target":367,"w":1.9},{"source":0,"target":373,"w":1.9},{"source":44,"target":376,"w":1.9},{"source":0,"target":397,"w":1.9},{"source":0,"target":398,"w":1.9},{"source":41,"target":410,"w":1.9},{"source":46,"target":414,"w":1.9},{"source":37,"target":418,"w":1.9},{"source":44,"target":419,"w":1.9},{"source":74,"target":437,"w":1.9},{"source":0,"target":451,"w":1.9},{"source":41,"target":461,"w":1.9},{"source":37,"target":463,"w":1.9},{"source":41,"target":466,"w":1.9},{"source":41,"target":471,"w":1.9},{"source":41,"target":474,"w":1.9},{"source":77,"target":479,"w":1.9},{"source":41,"target":485,"w":1.9},{"source":44,"target":494,"w":1.9},{"source":595,"target":503,"w":1.9},{"source":77,"target":507,"w":1.9},{"source":665,"target":508,"w":1.9},{"source":260,"target":510,"w":1.9},{"source":63,"target":511,"w":1.9},{"source":44,"target":512,"w":1.9},{"source":267,"target":514,"w":1.9},{"source":41,"target":517,"w":1.9},{"source":465,"target":523,"w":1.9},{"source":46,"target":529,"w":1.9},{"source":41,"target":536,"w":1.9},{"source":41,"target":537,"w":1.9},{"source":173,"target":597,"w":1.9},{"source":44,"target":599,"w":1.9},{"source":41,"target":608,"w":1.9},{"source":627,"target":635,"w":1.9},{"source":646,"target":641,"w":1.9},{"source":646,"target":689,"w":1.9},{"source":77,"target":715,"w":1.9},{"source":0,"target":741,"w":1.9},{"source":655,"target":759,"w":1.9},{"source":72,"target":879,"w":1.9},{"source":0,"target":904,"w":1.9},{"source":891,"target":912,"w":1.9},{"source":646,"target":955,"w":1.9}]}